{
    "fluentMethods": true,
    "relationships": [
        {
            "relationshipType": "many-to-one",
            "relationshipValidateRules": "required",
            "relationshipName": "relation",
            "otherEntityName": "defRelation",
            "otherEntityField": "code"
        },
        {
            "relationshipType": "many-to-one",
            "relationshipValidateRules": "required",
            "relationshipName": "itemSource",
            "otherEntityName": "defItem",
            "otherEntityField": "code"
        },
        {
            "relationshipType": "many-to-one",
            "relationshipName": "itemTarget",
            "otherEntityName": "defItem",
            "otherEntityField": "code"
        }
    ],
    "fields": [
        {
            "fieldName": "answer",
            "fieldType": "String",
            "fieldValidateRules": [
                "maxlength"
            ],
            "fieldValidateRulesMaxlength": 20
        }
    ],
    "changelogDate": "20180225093035",
    "entityTableName": "def_answer",
    "dto": "no",
    "pagination": "no",
    "service": "serviceImpl",
    "jpaMetamodelFiltering": false,
    "enableEntityAudit": true
}
